{
    "alencia": "Alencia",
    "ambitious-tywin": "Ambitious Tywin",
    "apocalypse-ravi": "Apocalypse Ravi",
    "aramintha": "Aramintha",
    "arbiter-vildred": "Arbiter Vildred",
    "archdemons-shadow": "Archdemon's Shadow",
    "baal-sezan": "Baal & Sezan",
    "baiken": "Baiken",
    "basar": "Basar",
    "bellona": "Bellona",
    "blood-moon-haste": "Blood Moon Haste",
    "briar-witch-iseria": "Briar Witch Iseria",
    "cecilia": "Cecilia",
    "celine": "Celine",
    "cerise": "Cerise",
    "cermia": "Cermia",
    "charles": "Charles",
    "charlotte": "Charlotte",
    "chloe": "Chloe",
    "choux": "Choux",
    "dark-corvus": "Dark Corvus",
    "desert-jewel-basar": "Desert Jewel Basar",
    "destina": "Destina",
    "diene": "Diene",
    "dizzy": "Dizzy",
    "elena": "Elena",
    "elphelt": "Elphelt",
    "ervalen": "Ervalen",
    "fairytale-tenebria": "Fairytale Tenebria",
    "faithless-lidica": "Faithless Lidica",
    "fallen-cecilia": "Fallen Cecilia",
    "flan": "Flan",
    "haste": "Haste",
    "holiday-yufine": "Holiday Yufine",
    "iseria": "Iseria",
    "judge-kise": "Judge Kise",
    "kawerik": "Kawerik",
    "kayron": "Kayron",
    "ken": "Ken",
    "kise": "Kise",
    "krau": "Krau",
    "landy": "Landy",
    "last-rider-krau": "Last Rider Krau",
    "lidica": "Lidica",
    "lilias": "Lilias",
    "lilibet": "Lilibet",
    "little-queen-charlotte": "Little Queen Charlotte",
    "ludwig": "Ludwig",
    "luluca": "Luluca",
    "luna": "Luna",
    "maid-chloe": "Maid Chloe",
    "martial-artist-ken": "Martial Artist Ken",
    "melissa": "Melissa",
    "mort": "Mort",
    "mui": "Mui",
    "operator-sigret": "Operator Sigret",
    "pavel": "Pavel",
    "politis": "Politis",
    "ravi": "Ravi",
    "ray": "Ray",
    "remnant-violet": "Remnant Violet",
    "roana": "Roana",
    "ruele-of-light": "Ruele of Light",
    "sage-baal-sezan": "Sage Baal & Sezan",
    "seaside-bellona": "Seaside Bellona",
    "sez": "Sez",
    "sigret": "Sigret",
    "silver-blade-aramintha": "Silver Blade Aramintha",
    "sol": "Sol",
    "specimen-sez": "Specimen Sez",
    "specter-tenebria": "Specter Tenebria",
    "tamarinne": "Tamarinne",
    "tenebria": "Tenebria",
    "top-model-luluca": "Top Model Luluca",
    "tywin": "Tywin",
    "vildred": "Vildred",
    "violet": "Violet",
    "vivian": "Vivian",
    "yufine": "Yufine",
    "yuna": "Yuna",
    "zeno": "Zeno",
    "achates": "Achates",
    "angelica": "Angelica",
    "armin": "Armin",
    "assassin-cartuja": "Assassin Cartuja",
    "assassin-cidd": "Assassin Cidd",
    "assassin-coli": "Assassin Coli",
    "auxiliary-lots": "Auxiliary Lots",
    "benevolent-romann": "Benevolent Romann",
    "blaze-dingo": "Blaze Dingo",
    "blood-blade-karin": "Blood Blade Karin",
    "cartuja": "Cartuja",
    "celestial-mercedes": "Celestial Mercedes",
    "challenger-dominiel": "Challenger Dominiel",
    "champion-zerato": "Champion Zerato",
    "cidd": "Cidd",
    "clarissa": "Clarissa",
    "coli": "Coli",
    "corvus": "Corvus",
    "crescent-moon-rin": "Crescent Moon Rin",
    "crimson-armin": "Crimson Armin",
    "crozet": "Crozet",
    "dingo": "Dingo",
    "dominiel": "Dominiel",
    "fighter-maya": "Fighter Maya",
    "free-spirit-tieria": "Free Spirit Tieria",
    "furious": "Furious",
    "general-purrgis": "General Purrgis",
    "guider-aither": "Guider Aither",
    "karin": "Karin",
    "khawana": "Khawana",
    "khawazu": "Khawazu",
    "kitty-clarissa": "Kitty Clarissa",
    "kizuna-ai": "Kizuna AI",
    "leo": "Leo",
    "lots": "Lots",
    "maya": "Maya",
    "mercedes": "Mercedes",
    "purrgis": "Purrgis",
    "rin": "Rin",
    "roaming-warrior-leo": "Roaming Warrior Leo",
    "romann": "Romann",
    "rose": "Rose",
    "schuri": "Schuri",
    "serila": "Serila",
    "shadow-rose": "Shadow Rose",
    "shooting-star-achates": "Shooting Star Achates",
    "silk": "Silk",
    "sinful-angelica": "Sinful Angelica",
    "surin": "Surin",
    "tempest-surin": "Tempest Surin",
    "troublemaker-crozet": "Troublemaker Crozet",
    "wanderer-silk": "Wanderer Silk",
    "watcher-schuri": "Watcher Schuri",
    "zerato": "Zerato",
    "adlay": "Adlay",
    "adventurer-ras": "Adventurer Ras",
    "ainos": "Ainos",
    "ains": "Ains",
    "aither": "Aither",
    "alexa": "Alexa",
    "allrounder-wanda": "All-Rounder Wanda",
    "angelic-montmorancy": "Angelic Montmorancy",
    "arowell": "Arowell",
    "azalea": "Azalea",
    "bask": "Bask",
    "batisse": "Batisse",
    "butcher-corps-inquisitor": "Butcher Corps Inquisitor",
    "captain-rikoris": "Captain Rikoris",
    "carmainerose": "Carmainerose",
    "carrot": "Carrot",
    "celeste": "Celeste",
    "chaos-inquisitor": "Chaos Inquisitor",
    "chaos-sect-axe": "Chaos Sect Axe",
    "church-of-ilryos-axe": "Church of Ilryos Axe",
    "commander-lorina": "Commander Lorina",
    "doll-maker-pearlhorizon": "Doll Maker Pearlhorizon",
    "doris": "Doris",
    "eaton": "Eaton",
    "elson": "Elson",
    "enott": "Enott",
    "falconer-kluri": "Falconer Kluri",
    "glenn": "Glenn",
    "gloomyrain": "Gloomyrain",
    "godmother": "Godmother",
    "gunther": "Gunther",
    "hataan": "Hataan",
    "hazel": "Hazel",
    "helga": "Helga",
    "hurado": "Hurado",
    "ian": "Ian",
    "jecht": "Jecht",
    "jena": "Jena",
    "judith": "Judith",
    "kikirat-v2": "Kikirat v2",
    "kiris": "Kiris",
    "kluri": "Kluri",
    "lena": "Lena",
    "lorina": "Lorina",
    "magic-scholar-doris": "Magic Scholar Doris",
    "mascot-hazel": "Mascot Hazel",
    "mercenary-helga": "Mercenary Helga",
    "mirsa": "Mirsa",
    "mistychain": "Mistychain",
    "montmorancy": "Montmorancy",
    "mucacha": "Mucacha",
    "nemunas": "Nemunas",
    "otillie": "Otillie",
    "pearlhorizon": "Pearlhorizon",
    "pyllis": "Pyllis",
    "ras": "Ras",
    "requiemroar": "Requiemroar",
    "researcher-carrot": "Researcher Carrot",
    "righteous-thief-roozid": "Righteous Thief Roozid",
    "rikoris": "Rikoris",
    "rima": "Rima",
    "roozid": "Roozid",
    "sonia": "Sonia",
    "sven": "Sven",
    "taranor-guard": "Taranor Guard",
    "taranor-royal-guard": "Taranor Royal Guard",
    "tieria": "Tieria",
    "wanda": "Wanda",
    "zealot-carmainerose": "Zealot Carmainerose",
    "a-little-queens-huge-crown": "A Little Queen's Huge Crown",
    "abyssal-crown": "Abyssal Crown",
    "alabastron": "Alabastron",
    "alencinoxs-wrath": "Alencinox's Wrath",
    "alexas-basket": "Alexa's Basket",
    "ancient-dragons-legacy": "Ancient Dragon's Legacy",
    "bastion-of-perlutia": "Bastion of Perlutia",
    "black-hand-of-the-goddess": "Black Hand of the Goddess",
    "bloodseared-moon": "Blood-Seared Moon",
    "bloodstone": "Bloodstone",
    "bloody-rose": "Bloody Rose",
    "border-coin": "Border Coin",
    "celestine": "Celestine",
    "champions-trophy": "Champion's Trophy",
    "chatty": "Chatty",
    "circus-fantasia": "Circus Fantasia",
    "cradle-of-life": "Cradle of Life",
    "creation-destruction": "Creation & Destruction",
    "crimson-moon-of-nightmares": "Crimson Moon of Nightmares",
    "crown-of-glory": "Crown of Glory",
    "cruel-mischief": "Cruel Mischief",
    "dignus-orb": "Dignus Orb",
    "doctors-bag": "Doctor's Bag",
    "doubleedged-decrescent": "Double-Edged Decrescent",
    "draco-plate": "Draco Plate",
    "durandal": "Durandal",
    "dux-noctis": "Dux Noctis",
    "elbris-ritual-sword": "Elbris Ritual Sword",
    "eticas-scepter": "Etica's Scepter",
    "fairy-tale-for-a-nightmare": "Fairy Tale for a Nightmare",
    "guiding-light": "Guiding Light",
    "holy-sacrifice": "Holy Sacrifice",
    "idols-cheer": "Idol's Cheer",
    "iron-fan": "Iron Fan",
    "junkyard-dog": "Junkyard Dog",
    "justice-for-all": "Justice for All",
    "knowledge-seed": "Knowledge Seed",
    "last-teatime": "Last Teatime",
    "manica-of-control": "Manica of Control",
    "manifu": "Manifu",
    "merciless-glutton": "Merciless Glutton",
    "ms-confille": "Ms. Confille",
    "necro-undine": "Necro & Undine",
    "noble-oath": "Noble Oath",
    "otherworldly-machinery": "Otherworldly Machinery",
    "proof-of-valor": "Proof of Valor",
    "reingars-special-drink": "Reingar's Special Drink",
    "rhianna-luciella": "Rhianna & Luciella",
    "rise-of-a-monarch": "Rise of a Monarch",
    "rod-of-amaryllis": "Rod of Amaryllis",
    "samsara-prayer-beads": "Samsara Prayer Beads",
    "secret-art-storm-sword": "Secret Art - Storm Sword",
    "shepherd-of-the-hollow": "Shepherd of the Hollow",
    "shimadra-staff": "Shimadra Staff",
    "sigurd-scythe": "Sigurd Scythe",
    "snow-crystal": "Snow Crystal",
    "song-of-stars": "Song of Stars",
    "spirits-breath": "Spirit's Breath",
    "star-piercer": "Star Piercer",
    "stella-harpa": "Stella Harpa",
    "sword-of-ezera": "Sword of Ezera",
    "sword-of-holy-light": "Sword of Holy Light",
    "sword-of-judgment": "Sword of Judgment",
    "sword-of-summer-twilight": "Sword of Summer Twilight",
    "time-matter": "Time Matter",
    "torn-sleeve": "Torn Sleeve",
    "touch-of-rekos": "Touch of Rekos",
    "uberiuss-tooth": "Uberius's Tooth",
    "unfading-memories": "Unfading Memories",
    "unseen-observer": "Unseen Observer",
    "violet-talisman": "Violet Talisman",
    "wall-of-order": "Wall of Order",
    "wind-rider": "Wind Rider",
    "adamant-shield": "Adamant Shield",
    "ambrote": "Ambrote",
    "andres-crossbow": "Andre's Crossbow",
    "aurius": "Aurius",
    "barthezs-orbuculum": "Barthez's Orbuculum",
    "bloody-warhammer": "Bloody Warhammer",
    "card-of-small-miracles": "Card of Small Miracles",
    "celestial-spear": "Celestial Spear",
    "crimson-seed": "Crimson Seed",
    "dust-devil": "Dust Devil",
    "els-fist": "El's Fist",
    "elyhas-knife": "Elyha's Knife",
    "eternus": "Eternus",
    "flower-shower": "Flower Shower",
    "golden-cocoa-cookie": "Golden Cocoa Cookie",
    "hell-cutter": "Hell Cutter",
    "hilag-lance": "Hilag Lance",
    "iela-violin": "Iela Violin",
    "infinity-basket": "Infinity Basket",
    "kaladra": "Kal'adra",
    "love-potion": "Love Potion",
    "magarahas-tome": "Magaraha's Tome",
    "midnight-bloom": "Midnight Bloom",
    "moonlight-dreamblade": "Moonlight Dreamblade",
    "new-year-cookies": "New Year Cookies",
    "one-year-of-gratitude": "One Year of Gratitude",
    "portrait-of-the-saviors": "Portrait of the Saviors",
    "radiant-forever": "Radiant Forever",
    "rainbow-scale": "Rainbow Scale",
    "rosa-hargana": "Rosa Hargana",
    "santa-muerte": "Santa Muerte",
    "sashe-ithanes": "Sashe Ithanes",
    "sepulcrum": "Sepulcrum",
    "shepherds-of-chaos": "Shepherds of Chaos",
    "silver-rain": "Silver Rain",
    "siraren": "Sira-Ren",
    "spooky-solayu-stories": "Spooky Solayu Stories",
    "steadfast-gatekeeper": "Steadfast Gatekeeper",
    "strak-gauntlet": "Strak Gauntlet",
    "succubus-mirror": "Succubus Mirror",
    "tagehels-ancient-book": "Tagehel's Ancient Book",
    "tear-of-the-desert": "Tear of the Desert",
    "to-a-new-world": "To a New World",
    "waters-origin": "Water's Origin",
    "wondrous-potion-vial": "Wondrous Potion Vial",
    "xvi-the-tower": "XVI. The Tower",
    "alsacian-spear": "Alsacian Spear",
    "ancient-sheath": "Ancient Sheath",
    "aqua-rose": "Aqua Rose",
    "ascending-axe": "Ascending Axe",
    "atmas-portal": "Atma's Portal",
    "butterfly-mandolin": "Butterfly Mandolin",
    "cursed-compass": "Cursed Compass",
    "daydream-joker": "Daydream Joker",
    "devils-brand": "Devil's Brand",
    "egg-of-delusion": "Egg of Delusion",
    "envoys-pipe": "Envoy's Pipe",
    "exorcists-tonfa": "Exorcist's Tonfa",
    "forest-totem": "Forest Totem",
    "goblins-lamp": "Goblin's Lamp",
    "grail-of-blood": "Grail of Blood",
    "labyrinth-cube": "Labyrinth Cube",
    "mighty-yaksha": "Mighty Yaksha",
    "oath-key": "Oath Key",
    "prophetic-candlestick": "Prophetic Candlestick",
    "ranons-memorandum": "Ranon's Memorandum",
    "ruby-essence": "Ruby Essence",
    "sword-of-the-morning": "Sword of the Morning",
    "timeless-anchor": "Timeless Anchor"
}